Metadata-Version: 2.1
Name: Enkryptor
Version: 0.1.1.post1
Summary: A Python module designed to be able to encrypt almost any kind of data as easily as possible for you.
Home-page: https://github.com/FrankR-7/Enkryptor
Author: furankii
Author-email: frank_rv@yahoo.com
License: MIT
Download-URL: https://github.com/FrankR-7/Enkryptor/archive/refs/tags/v0.1.1-post1.tar.gz
Keywords: encryption,security,auth,authenthication
Platform: UNKNOWN
Classifier: Development Status :: 5 - Production/Stable
Classifier: Intended Audience :: Developers
Classifier: Topic :: Software Development :: Build Tools
Classifier: License :: OSI Approved :: MIT License
Classifier: Programming Language :: Python :: 3
Classifier: Programming Language :: Python :: 3.4
Classifier: Programming Language :: Python :: 3.5
Classifier: Programming Language :: Python :: 3.6
Classifier: Programming Language :: Python :: 3.7
Classifier: Programming Language :: Python :: 3.8
License-File: LICENSE.txt
